{
  "generated_at": "2026-05-29T21:06:51.364456+00:00",
  "seasons_used": [
    2021,
    2022,
    2023,
    2024,
    2025,
    2026
  ],
  "total_graded": 13837,
  "source_breakdown": {
    "historical_backtest": 12999,
    "live_history": 838
  },
  "platt_params": {
    "a": 1.22417,
    "b": -0.002199
  },
  "logistic_params": {
    "midpoint": 7.5,
    "slope": 0.45
  },
  "brier_score": {
    "raw_model": 0.244838,
    "calibrated": 0.244462
  },
  "overall_win_rate": 0.5586,
  "win_rates_by_confidence": {
    "50-55%": {
      "n": 7872,
      "win_rate": 0.5029
    },
    "55-60%": {
      "n": 4298,
      "win_rate": 0.5468
    },
    "60-65%": {
      "n": 1381,
      "win_rate": 0.5981
    },
    "65%+": {
      "n": 286,
      "win_rate": 0.6888
    }
  },
  "calibration_curve": [
    {
      "bin": "0.30-0.40",
      "n": 180,
      "model_prob_mean": 0.38,
      "actual_win_rate": 0.3389
    },
    {
      "bin": "0.40-0.50",
      "n": 3729,
      "model_prob_mean": 0.4665,
      "actual_win_rate": 0.4545
    },
    {
      "bin": "0.50-0.60",
      "n": 8441,
      "model_prob_mean": 0.544,
      "actual_win_rate": 0.5466
    },
    {
      "bin": "0.60-0.70",
      "n": 1458,
      "model_prob_mean": 0.6273,
      "actual_win_rate": 0.6427
    },
    {
      "bin": "0.70-0.80",
      "n": 28,
      "model_prob_mean": 0.7187,
      "actual_win_rate": 0.8571
    },
    {
      "bin": "0.80-0.90",
      "n": 1,
      "model_prob_mean": 0.8209,
      "actual_win_rate": 1.0
    }
  ]
}