{"generated_at":"2026-05-29T21:03:41.977899+00:00","date":"2026-05-29","game_count":15,"games":[{"gamePk":824515,"game_time_utc":"2026-05-29T22:40:00Z","game_time_et":"6:40 PM ET","home_team":"Cincinnati Reds","away_team":"Atlanta Braves","home_sp_id":663978,"away_sp_id":656550,"venue":"Great American Ball Park","park_run_factor":108.0,"weather":{"temp_f":83,"wind_mph":3,"wind_dir":"3 mph blowing In","blowing_out":false},"odds":{"home_ml":116,"away_ml":-126,"total":9.5,"over_price":105,"under_price":-118,"line_movement":{"ml_move":0.029,"opening_home_ml":130,"current_home_ml":116}},"game_status":"preview","home_score":0,"away_score":0,"current_inning":1,"inning_state":"Top 1st","outs":0,"home_sp":{"name":"Paddack, Chris","mlbam_id":663978,"throws":null,"season":{"xera":4.32,"xba":0.267,"whiff_pct":0.195,"chase_pct":0.322,"k_pct":0.17,"bb_pct":null,"rv100":null,"era":6.86,"ip":null},"recent":{"k_pct":0.17,"bb_pct":0.085,"whiff_pct":0.195,"chase_pct":0.322,"starts_n":2},"last_start":{"deviation":1.08,"era_est":5.4,"ip":5.0},"trend_flags":["Regression candidate: ERA (6.86) >> xERA (4.32)"]},"away_sp":{"name":"Holmes, Grant","mlbam_id":656550,"throws":null,"season":{"xera":4.17,"xba":0.236,"whiff_pct":0.293,"chase_pct":0.358,"k_pct":0.302,"bb_pct":null,"rv100":null,"era":3.78,"ip":null},"recent":{"k_pct":0.302,"bb_pct":0.111,"whiff_pct":0.293,"chase_pct":0.358,"starts_n":3},"last_start":{"deviation":-0.57,"era_est":3.6,"ip":5.0},"trend_flags":[]},"home_lineup":[{"name":"Dunn, Blake","mlbam_id":694362,"batting_order":1,"xwoba":0.298,"woba":0.384,"avg_ev":null,"hard_hit_pct":null,"k_pct":null,"bb_pct":null,"trend_flags":["Hot: 7H in last 5 games"]},{"name":"De La Cruz, Elly","mlbam_id":682829,"batting_order":2,"xwoba":0.363,"woba":0.374,"avg_ev":94.1,"hard_hit_pct":0.53,"k_pct":null,"bb_pct":null,"trend_flags":[]},{"name":"Bleday, JJ","mlbam_id":668709,"batting_order":3,"xwoba":0.403,"woba":0.407,"avg_ev":90.8,"hard_hit_pct":0.474,"k_pct":null,"bb_pct":null,"trend_flags":[]},{"name":"Stewart, Sal","mlbam_id":701398,"batting_order":4,"xwoba":0.37,"woba":0.36,"avg_ev":90.7,"hard_hit_pct":0.41,"k_pct":null,"bb_pct":null,"trend_flags":[]},{"name":"Su\u00e1rez, Eugenio","mlbam_id":553993,"batting_order":5,"xwoba":0.298,"woba":0.314,"avg_ev":86.1,"hard_hit_pct":0.239,"k_pct":null,"bb_pct":null,"trend_flags":[]},{"name":"Lowe, Nathaniel","mlbam_id":663993,"batting_order":6,"xwoba":0.392,"woba":0.396,"avg_ev":90.5,"hard_hit_pct":0.471,"k_pct":null,"bb_pct":null,"trend_flags":["Hot: 7H in last 5 games"]},{"name":"Steer, Spencer","mlbam_id":668715,"batting_order":7,"xwoba":0.372,"woba":0.341,"avg_ev":89.8,"hard_hit_pct":0.381,"k_pct":null,"bb_pct":null,"trend_flags":[]},{"name":"Stephenson, Tyler","mlbam_id":663886,"batting_order":8,"xwoba":0.326,"woba":0.288,"avg_ev":90.6,"hard_hit_pct":0.441,"k_pct":null,"bb_pct":null,"trend_flags":[]},{"name":"Friedl, TJ","mlbam_id":670770,"batting_order":9,"xwoba":0.252,"woba":0.244,"avg_ev":88.0,"hard_hit_pct":0.287,"k_pct":null,"bb_pct":null,"trend_flags":[]}],"away_lineup":[{"name":"Acu\u00f1a Jr., Ronald","mlbam_id":660670,"batting_order":1,"xwoba":0.374,"woba":0.328,"avg_ev":89.6,"hard_hit_pct":0.442,"k_pct":null,"bb_pct":null,"trend_flags":[]},{"name":"Harris II, Michael","mlbam_id":671739,"batting_order":2,"xwoba":0.388,"woba":0.374,"avg_ev":93.4,"hard_hit_pct":0.561,"k_pct":null,"bb_pct":null,"trend_flags":["Hot: 7H in last 5 games"]},{"name":"Olson, Matt","mlbam_id":621566,"batting_order":3,"xwoba":0.38,"woba":0.382,"avg_ev":93.3,"hard_hit_pct":0.515,"k_pct":null,"bb_pct":null,"trend_flags":[]},{"name":"Albies, Ozzie","mlbam_id":645277,"batting_order":4,"xwoba":0.305,"woba":0.341,"avg_ev":86.5,"hard_hit_pct":0.272,"k_pct":null,"bb_pct":null,"trend_flags":["Hot: 7H in last 5 games"]},{"name":"Smith, Dominic","mlbam_id":642086,"batting_order":5,"xwoba":0.362,"woba":0.375,"avg_ev":89.4,"hard_hit_pct":0.408,"k_pct":null,"bb_pct":null,"trend_flags":[]},{"name":"Riley, Austin","mlbam_id":663586,"batting_order":6,"xwoba":0.305,"woba":0.297,"avg_ev":91.0,"hard_hit_pct":0.455,"k_pct":null,"bb_pct":null,"trend_flags":[]},{"name":"Yastrzemski, Mike","mlbam_id":573262,"batting_order":7,"xwoba":0.283,"woba":0.305,"avg_ev":90.3,"hard_hit_pct":0.379,"k_pct":null,"bb_pct":null,"trend_flags":[]},{"name":"Mateo, Jorge","mlbam_id":622761,"batting_order":8,"xwoba":0.339,"woba":0.372,"avg_ev":null,"hard_hit_pct":null,"k_pct":null,"bb_pct":null,"trend_flags":[]},{"name":"Tromp, Chadwick","mlbam_id":644433,"batting_order":9,"xwoba":0.177,"woba":0.287,"avg_ev":null,"hard_hit_pct":null,"k_pct":null,"bb_pct":null,"trend_flags":[]}],"lineup_status":"official","prediction":{"home_win_pct":0.4268,"away_win_pct":0.5732,"predicted_home_runs":4.8,"predicted_away_runs":4.8,"predicted_total":9.6,"narrative":"Holmes' elite strikeout rate (30.2%) and whiff percentage (29.3%) directly challenge Cincinnati's below-average lineup (xwOBA 0.342), positioning Atlanta as the sharper side despite a -0.094 pitcher disadvantage. Paddack presents significant regression risk with his 2.54-run ERA gap (6.86 actual vs 4.32 xERA), compounded by his last start exceeding expectation by +1.08 runs and facing a superior Braves offense (xwOBA 0.324). The model's 42.7% home win probability underprices Cincinnati relative to Vegas' +116 odds, with the slight pitcher edge to Atlanta offsetting the modest home-field advantage at a park inflating run environment (108 RF).","model_edge_ml":-0.0269,"pitcher_score_diff":-0.094,"pick_tier":null,"model_signals":{"pitcher_score_home":0.449,"pitcher_score_away":0.543,"lineup_score_home":0.573,"lineup_score_away":0.53,"comps_home_win_rate":0.5,"comps_count":30,"park_modifier":0.008,"weather_modifier":0.1,"rest_modifier":0.04,"home_rest_days":1,"away_rest_days":0,"bullpen_xera_home":null,"bullpen_xera_away":null,"bp_ip_last_3_home":null,"bp_ip_last_3_away":null,"last_start_dev_home":0.92,"last_start_dev_away":-1.12,"last_3_start_dev_home":0.92,"last_3_start_dev_away":-1.12,"last_start_pitches_home":null,"last_start_pitches_away":null,"umpire":"Ryan Blakney","consensus_suppressed":false}},"away_record":{"wins":38,"losses":19,"streak":"W1","l10_w":6,"l10_l":4},"home_record":{"wins":29,"losses":26,"streak":"L1","l10_w":5,"l10_l":5}},{"gamePk":822732,"game_time_utc":"2026-05-29T22:45:00Z","game_time_et":"6:45 PM ET","home_team":"Washington Nationals","away_team":"San Diego Padres","home_sp_id":687606,"away_sp_id":608337,"venue":"Nationals Park","park_run_factor":99.0,"weather":{"temp_f":79,"wind_mph":10,"wind_dir":"10 mph blowing In","blowing_out":false},"odds":{"home_ml":-114,"away_ml":105,"total":9.5,"over_price":105,"under_price":-118,"line_movement":{"total_move":0.5,"opening_total":9.0,"current_total":9.5,"ml_move":0.034,"opening_home_ml":100,"current_home_ml":-114}},"game_status":"preview","home_score":0,"away_score":0,"current_inning":1,"inning_state":"Top 1st","outs":0,"home_sp":{"name":"Schultz, Paxton","mlbam_id":687606,"throws":null,"season":{"xera":4.23,"xba":0.255,"whiff_pct":0.189,"chase_pct":0.279,"k_pct":0.31,"bb_pct":null,"rv100":null,"era":5.3,"ip":null},"recent":{"k_pct":0.333,"bb_pct":0.111,"whiff_pct":0.189,"chase_pct":0.279,"starts_n":1},"last_start":{},"trend_flags":["Regression candidate: ERA (5.30) >> xERA (4.23)"]},"away_sp":{"name":"Giolito, Lucas","mlbam_id":608337,"throws":null,"season":{"xera":3.92,"xba":0.208,"whiff_pct":0.188,"chase_pct":0.17,"k_pct":0.122,"bb_pct":null,"rv100":null,"era":2.7,"ip":null},"recent":{"k_pct":0.122,"bb_pct":0.195,"whiff_pct":0.188,"chase_pct":0.17,"starts_n":2},"last_start":{"deviation":-3.0,"era_est":0.0,"ip":5.0},"trend_flags":["Outperforming xERA: ERA (2.70) << xERA (3.92)"]},"home_lineup":[{"name":"Wood, James","mlbam_id":695578,"batting_order":1,"xwoba":0.44,"woba":0.416,"avg_ev":96.6,"hard_hit_pct":0.612,"k_pct":null,"bb_pct":null,"trend_flags":["Hot: 9H in last 5 games"]},{"name":"Garc\u00eda Jr., Luis","mlbam_id":671277,"batting_order":2,"xwoba":0.315,"woba":0.309,"avg_ev":92.4,"hard_hit_pct":0.479,"k_pct":null,"bb_pct":null,"trend_flags":[]},{"name":"Mead, Curtis","mlbam_id":678554,"batting_order":3,"xwoba":0.374,"woba":0.365,"avg_ev":89.1,"hard_hit_pct":0.455,"k_pct":null,"bb_pct":null,"trend_flags":["Hot: 6H in last 5 games"]},{"name":"Abrams, CJ","mlbam_id":682928,"batting_order":4,"xwoba":0.374,"woba":0.404,"avg_ev":89.9,"hard_hit_pct":0.413,"k_pct":null,"bb_pct":null,"trend_flags":[]},{"name":"Crews, Dylan","mlbam_id":686611,"batting_order":5,"xwoba":0.258,"woba":0.278,"avg_ev":null,"hard_hit_pct":null,"k_pct":null,"bb_pct":null,"trend_flags":["Hot: 6H in last 5 games"]},{"name":"Lile, Daylen","mlbam_id":695734,"batting_order":6,"xwoba":0.326,"woba":0.325,"avg_ev":88.1,"hard_hit_pct":0.381,"k_pct":null,"bb_pct":null,"trend_flags":[]},{"name":"Young, Jacob","mlbam_id":696285,"batting_order":7,"xwoba":0.319,"woba":0.299,"avg_ev":89.0,"hard_hit_pct":0.362,"k_pct":null,"bb_pct":null,"trend_flags":[]},{"name":"Ruiz, Keibert","mlbam_id":660688,"batting_order":8,"xwoba":0.26,"woba":0.327,"avg_ev":90.0,"hard_hit_pct":0.413,"k_pct":null,"bb_pct":null,"trend_flags":["Hot: 7H in last 5 games"]},{"name":"Nu\u00f1ez, Nasim","mlbam_id":683083,"batting_order":9,"xwoba":0.269,"woba":0.242,"avg_ev":84.4,"hard_hit_pct":0.186,"k_pct":null,"bb_pct":null,"trend_flags":[]}],"away_lineup":[{"name":"Tatis Jr., Fernando","mlbam_id":665487,"batting_order":1,"xwoba":0.345,"woba":0.294,"avg_ev":90.0,"hard_hit_pct":0.519,"k_pct":null,"bb_pct":null,"trend_flags":["Hot: 8H in last 5 games"]},{"name":"Sheets, Gavin","mlbam_id":657757,"batting_order":2,"xwoba":0.341,"woba":0.359,"avg_ev":89.5,"hard_hit_pct":0.457,"k_pct":null,"bb_pct":null,"trend_flags":[]},{"name":"Bogaerts, Xander","mlbam_id":593428,"batting_order":3,"xwoba":0.324,"woba":0.307,"avg_ev":87.4,"hard_hit_pct":0.359,"k_pct":null,"bb_pct":null,"trend_flags":[]},{"name":"Machado, Manny","mlbam_id":592518,"batting_order":4,"xwoba":0.308,"woba":0.27,"avg_ev":90.0,"hard_hit_pct":0.427,"k_pct":null,"bb_pct":null,"trend_flags":[]},{"name":"Merrill, Jackson","mlbam_id":701538,"batting_order":5,"xwoba":0.305,"woba":0.264,"avg_ev":89.1,"hard_hit_pct":0.458,"k_pct":null,"bb_pct":null,"trend_flags":[]},{"name":"Andujar, Miguel","mlbam_id":609280,"batting_order":6,"xwoba":0.294,"woba":0.326,"avg_ev":88.8,"hard_hit_pct":0.394,"k_pct":null,"bb_pct":null,"trend_flags":[]},{"name":"Laureano, Ram\u00f3n","mlbam_id":657656,"batting_order":7,"xwoba":0.317,"woba":0.302,"avg_ev":88.7,"hard_hit_pct":0.434,"k_pct":null,"bb_pct":null,"trend_flags":[]},{"name":"France, Ty","mlbam_id":664034,"batting_order":8,"xwoba":0.324,"woba":0.351,"avg_ev":90.7,"hard_hit_pct":0.486,"k_pct":null,"bb_pct":null,"trend_flags":[]},{"name":"Fermin, Freddy","mlbam_id":666023,"batting_order":9,"xwoba":0.246,"woba":0.207,"avg_ev":85.7,"hard_hit_pct":0.25,"k_pct":null,"bb_pct":null,"trend_flags":["Cold: 0H in last 5 games"]}],"lineup_status":"official","prediction":{"home_win_pct":0.5021,"away_win_pct":0.4979,"predicted_home_runs":4.8,"predicted_away_runs":4.7,"predicted_total":9.5,"narrative":"Schultz carries significant negative regression risk with his ERA inflated 1.07 runs above xERA, while Giolito has dramatically outperformed his underlying metrics in recent starts\u2014the -3.00 ERA deviation flag signals he's due for regression toward his 3.92 xERA. The Padres' superior pitching profile (pitcher score diff -0.040 favoring away, Giolito's elite xERA) conflicts with modest home-team edge in lineup quality (+0.076), creating a tight matchup that the model prices at near-even (50.2% home win probability) despite Vegas favoring Washington at -114.","model_edge_ml":-0.0199,"pitcher_score_diff":-0.0395,"pick_tier":null,"model_signals":{"pitcher_score_home":0.432,"pitcher_score_away":0.472,"lineup_score_home":0.524,"lineup_score_away":0.448,"comps_home_win_rate":0.6333,"comps_count":30,"park_modifier":-0.001,"weather_modifier":-0.156,"rest_modifier":0.0,"home_rest_days":1,"away_rest_days":1,"bullpen_xera_home":null,"bullpen_xera_away":null,"bp_ip_last_3_home":null,"bp_ip_last_3_away":null,"last_start_dev_home":null,"last_start_dev_away":-1.32,"last_3_start_dev_home":null,"last_3_start_dev_away":-1.32,"last_start_pitches_home":null,"last_start_pitches_away":null,"umpire":"Mark Ripperger","consensus_suppressed":false}},"away_record":{"wins":31,"losses":24,"streak":"L4","l10_w":4,"l10_l":6},"home_record":{"wins":29,"losses":28,"streak":"L1","l10_w":6,"l10_l":4}},{"gamePk":823377,"game_time_utc":"2026-05-29T22:45:00Z","game_time_et":"6:45 PM ET","home_team":"Pittsburgh Pirates","away_team":"Minnesota Twins","home_sp_id":683003,"away_sp_id":671737,"venue":"PNC Park","park_run_factor":96.0,"weather":{"temp_f":77,"wind_mph":12,"wind_dir":"12 mph blowing In","blowing_out":false},"odds":{"home_ml":-127,"away_ml":117,"total":8.0,"over_price":-108,"under_price":-104},"game_status":"preview","home_score":null,"away_score":null,"current_inning":null,"inning_state":null,"outs":null,"home_sp":{"name":"Jared Jones","mlbam_id":683003,"throws":null,"season":{"xera":null,"xba":null,"whiff_pct":null,"chase_pct":null,"k_pct":null,"bb_pct":null,"rv100":null,"era":null,"ip":null},"recent":{},"last_start":{},"trend_flags":[]},"away_sp":{"name":"Bradley, Taj","mlbam_id":671737,"throws":null,"season":{"xera":3.63,"xba":0.227,"whiff_pct":0.314,"chase_pct":0.386,"k_pct":null,"bb_pct":null,"rv100":null,"era":2.77,"ip":null},"recent":{"k_pct":0.389,"bb_pct":0.111,"whiff_pct":0.314,"chase_pct":0.386,"starts_n":1},"last_start":{"deviation":-1.83,"era_est":1.8,"ip":5.0},"trend_flags":["Outperforming xERA: ERA (2.77) << xERA (3.63)"]},"home_lineup":[],"away_lineup":[{"name":"Buxton, Byron","mlbam_id":621439,"batting_order":1,"xwoba":0.335,"woba":0.385,"avg_ev":90.1,"hard_hit_pct":0.472,"k_pct":null,"bb_pct":null,"trend_flags":[]},{"name":"Lee, Brooks","mlbam_id":686797,"batting_order":2,"xwoba":0.269,"woba":0.314,"avg_ev":86.7,"hard_hit_pct":0.282,"k_pct":null,"bb_pct":null,"trend_flags":[]},{"name":"Clemens, Kody","mlbam_id":665019,"batting_order":3,"xwoba":0.328,"woba":0.32,"avg_ev":92.1,"hard_hit_pct":0.416,"k_pct":null,"bb_pct":null,"trend_flags":[]},{"name":"Bell, Josh","mlbam_id":605137,"batting_order":4,"xwoba":0.295,"woba":0.276,"avg_ev":89.9,"hard_hit_pct":0.416,"k_pct":null,"bb_pct":null,"trend_flags":[]},{"name":"Larnach, Trevor","mlbam_id":663616,"batting_order":5,"xwoba":0.314,"woba":0.34,"avg_ev":86.4,"hard_hit_pct":0.314,"k_pct":null,"bb_pct":null,"trend_flags":[]},{"name":"Martin, Austin","mlbam_id":668885,"batting_order":6,"xwoba":0.331,"woba":0.354,"avg_ev":86.4,"hard_hit_pct":0.317,"k_pct":null,"bb_pct":null,"trend_flags":[]},{"name":"Caratini, Victor","mlbam_id":605170,"batting_order":7,"xwoba":0.327,"woba":0.246,"avg_ev":88.9,"hard_hit_pct":0.373,"k_pct":null,"bb_pct":null,"trend_flags":[]},{"name":"Keaschall, Luke","mlbam_id":807712,"batting_order":8,"xwoba":0.281,"woba":0.286,"avg_ev":84.2,"hard_hit_pct":0.261,"k_pct":null,"bb_pct":null,"trend_flags":[]},{"name":"Gray, Tristan","mlbam_id":656484,"batting_order":9,"xwoba":0.316,"woba":0.297,"avg_ev":89.4,"hard_hit_pct":0.421,"k_pct":null,"bb_pct":null,"trend_flags":[]}],"lineup_status":"official","prediction":{"home_win_pct":0.525,"away_win_pct":0.475,"predicted_home_runs":3.9,"predicted_away_runs":3.9,"predicted_total":7.8,"narrative":"Bradley's ERA (2.77) significantly outpaces his xERA (3.63) with elite whiff rates (31.4%), suggesting sustainable stuff that hasn't fully regressed despite a -1.83 last-start variance\u2014the Twins' away lineup advantage (+0.111) is meaningful but offset by a modest pitching edge favoring Pittsburgh (-0.075 pitcher diff). The infield wind at PNC Park (96 park factor) suppresses the total to 7.8, aligning with Vegas's 8.0, though both sides maintain a muted consensus with the model's 52.5% home lean indicating minimal edge in what Vegas prices as a -127 home favorite.","model_edge_ml":-0.0233,"pitcher_score_diff":-0.0755,"pick_tier":null,"model_signals":{"pitcher_score_home":0.5,"pitcher_score_away":0.575,"lineup_score_home":0.5,"lineup_score_away":0.389,"comps_home_win_rate":0.3333,"comps_count":30,"park_modifier":-0.004,"weather_modifier":-0.174,"rest_modifier":0.0,"home_rest_days":0,"away_rest_days":0,"bullpen_xera_home":null,"bullpen_xera_away":null,"bp_ip_last_3_home":null,"bp_ip_last_3_away":null,"last_start_dev_home":null,"last_start_dev_away":-1.32,"last_3_start_dev_home":null,"last_3_start_dev_away":-1.32,"last_start_pitches_home":null,"last_start_pitches_away":null,"umpire":"Jansen Visconti","consensus_suppressed":true}},"away_record":{"wins":27,"losses":30,"streak":"L2","l10_w":6,"l10_l":4},"home_record":{"wins":29,"losses":28,"streak":"L2","l10_w":5,"l10_l":5}},{"gamePk":824835,"game_time_utc":"2026-05-29T23:05:00Z","game_time_et":"7:05 PM ET","home_team":"Baltimore Orioles","away_team":"Toronto Blue Jays","home_sp_id":669432,"away_sp_id":671936,"venue":"Oriole Park at Camden Yards","park_run_factor":97.0,"weather":{"temp_f":76,"wind_mph":9,"wind_dir":"9 mph blowing Out","blowing_out":true},"odds":{"home_ml":-111,"away_ml":102,"total":9.0,"over_price":104,"under_price":-117},"game_status":"preview","home_score":0,"away_score":0,"current_inning":1,"inning_state":"Top 1st","outs":0,"home_sp":{"name":"Rogers, Trevor","mlbam_id":669432,"throws":null,"season":{"xera":4.53,"xba":0.269,"whiff_pct":0.15,"chase_pct":0.282,"k_pct":0.127,"bb_pct":null,"rv100":null,"era":6.96,"ip":null},"recent":{"k_pct":0.127,"bb_pct":0.111,"whiff_pct":0.15,"chase_pct":0.282,"starts_n":3},"last_start":{"deviation":3.0,"era_est":8.53,"ip":4.2},"trend_flags":["Regression candidate: ERA (6.96) >> xERA (4.53)"]},"away_sp":{"name":"Macko, Adam","mlbam_id":671936,"throws":null,"season":{"xera":4.03,"xba":0.251,"whiff_pct":0.194,"chase_pct":0.39,"k_pct":null,"bb_pct":null,"rv100":null,"era":0.0,"ip":null},"recent":{},"last_start":{},"trend_flags":["Outperforming xERA: ERA (0.00) << xERA (4.03)"]},"home_lineup":[{"name":"Ward, Taylor","mlbam_id":621493,"batting_order":1,"xwoba":0.35,"woba":0.351,"avg_ev":89.3,"hard_hit_pct":0.392,"k_pct":null,"bb_pct":null,"trend_flags":[]},{"name":"Henderson, Gunnar","mlbam_id":683002,"batting_order":2,"xwoba":0.297,"woba":0.308,"avg_ev":89.5,"hard_hit_pct":0.446,"k_pct":null,"bb_pct":null,"trend_flags":[]},{"name":"Rutschman, Adley","mlbam_id":668939,"batting_order":3,"xwoba":0.367,"woba":0.363,"avg_ev":89.6,"hard_hit_pct":0.463,"k_pct":null,"bb_pct":null,"trend_flags":[]},{"name":"Alonso, Pete","mlbam_id":624413,"batting_order":4,"xwoba":0.361,"woba":0.327,"avg_ev":95.1,"hard_hit_pct":0.559,"k_pct":null,"bb_pct":null,"trend_flags":["Hot: 6H in last 5 games"]},{"name":"Basallo, Samuel","mlbam_id":694212,"batting_order":5,"xwoba":0.343,"woba":0.349,"avg_ev":92.9,"hard_hit_pct":0.491,"k_pct":null,"bb_pct":null,"trend_flags":[]},{"name":"Taveras, Leody","mlbam_id":665750,"batting_order":6,"xwoba":0.322,"woba":0.348,"avg_ev":87.4,"hard_hit_pct":0.311,"k_pct":null,"bb_pct":null,"trend_flags":["Hot: 7H in last 5 games"]},{"name":"Cowser, Colton","mlbam_id":681297,"batting_order":7,"xwoba":0.291,"woba":0.279,"avg_ev":85.3,"hard_hit_pct":0.303,"k_pct":null,"bb_pct":null,"trend_flags":[]},{"name":"Mayo, Coby","mlbam_id":691723,"batting_order":8,"xwoba":0.306,"woba":0.288,"avg_ev":91.6,"hard_hit_pct":0.473,"k_pct":null,"bb_pct":null,"trend_flags":[]},{"name":"Holliday, Jackson","mlbam_id":702616,"batting_order":9,"xwoba":0.286,"woba":0.289,"avg_ev":null,"hard_hit_pct":null,"k_pct":null,"bb_pct":null,"trend_flags":[]}],"away_lineup":[{"name":"Springer, George","mlbam_id":543807,"batting_order":1,"xwoba":0.304,"woba":0.295,"avg_ev":88.0,"hard_hit_pct":0.391,"k_pct":null,"bb_pct":null,"trend_flags":[]},{"name":"Clement, Ernie","mlbam_id":676391,"batting_order":2,"xwoba":0.28,"woba":0.335,"avg_ev":85.9,"hard_hit_pct":0.264,"k_pct":null,"bb_pct":null,"trend_flags":[]},{"name":"Guerrero Jr., Vladimir","mlbam_id":665489,"batting_order":3,"xwoba":0.364,"woba":0.341,"avg_ev":90.2,"hard_hit_pct":0.422,"k_pct":null,"bb_pct":null,"trend_flags":[]},{"name":"Okamoto, Kazuma","mlbam_id":672960,"batting_order":4,"xwoba":0.327,"woba":0.317,"avg_ev":92.8,"hard_hit_pct":0.519,"k_pct":null,"bb_pct":null,"trend_flags":[]},{"name":"Varsho, Daulton","mlbam_id":662139,"batting_order":5,"xwoba":0.308,"woba":0.33,"avg_ev":86.5,"hard_hit_pct":0.393,"k_pct":null,"bb_pct":null,"trend_flags":[]},{"name":"Unknown","mlbam_id":807727,"batting_order":6,"xwoba":null,"woba":null,"avg_ev":null,"hard_hit_pct":null,"k_pct":null,"bb_pct":null,"trend_flags":[]},{"name":"Straw, Myles","mlbam_id":664702,"batting_order":7,"xwoba":0.321,"woba":0.305,"avg_ev":86.6,"hard_hit_pct":0.268,"k_pct":null,"bb_pct":null,"trend_flags":[]},{"name":"Pi\u00f1ango, Yohendrick","mlbam_id":682818,"batting_order":8,"xwoba":0.312,"woba":0.334,"avg_ev":90.2,"hard_hit_pct":0.403,"k_pct":null,"bb_pct":null,"trend_flags":[]},{"name":"Valenzuela, Brandon","mlbam_id":678218,"batting_order":9,"xwoba":0.337,"woba":0.334,"avg_ev":88.9,"hard_hit_pct":0.386,"k_pct":null,"bb_pct":null,"trend_flags":[]}],"lineup_status":"official","prediction":{"home_win_pct":0.4586,"away_win_pct":0.5414,"predicted_home_runs":4.5,"predicted_away_runs":4.6,"predicted_total":9.1,"narrative":"Rogers' inflated ERA (6.96) masks underlying xERA of 4.53, but his last start showed +3.00 deviation suggesting recent control deterioration (11.1% BB%) that persists despite park-neutral metrics\u2014this creates vulnerability against Toronto's comparable lineup strength. Macko presents sharper strikeout stuff (19.4% whiff) and has outperformed his xERA, giving the away pitcher a -0.152 edge that the model reflects in its 45.9% home win probability, slightly favoring the underdog relative to Vegas' -111 pricing. Outfield wind (9 mph) aids fly balls at a run-suppressing park (97 factor), partially offsetting Rogers' control issues.","model_edge_ml":-0.0566,"pitcher_score_diff":-0.1516,"pick_tier":null,"model_signals":{"pitcher_score_home":0.383,"pitcher_score_away":0.535,"lineup_score_home":0.5,"lineup_score_away":0.423,"comps_home_win_rate":0.6333,"comps_count":30,"park_modifier":-0.003,"weather_modifier":0.0,"rest_modifier":0.0,"home_rest_days":0,"away_rest_days":0,"bullpen_xera_home":null,"bullpen_xera_away":null,"bp_ip_last_3_home":null,"bp_ip_last_3_away":null,"last_start_dev_home":3.0,"last_start_dev_away":null,"last_3_start_dev_home":3.0,"last_3_start_dev_away":null,"last_start_pitches_home":null,"last_start_pitches_away":null,"umpire":"Clint Vondrak","consensus_suppressed":false}},"away_record":{"wins":28,"losses":29,"streak":"W3","l10_w":7,"l10_l":3},"home_record":{"wins":26,"losses":31,"streak":"L1","l10_w":5,"l10_l":5}},{"gamePk":824433,"game_time_utc":"2026-05-29T23:10:00Z","game_time_et":"7:10 PM ET","home_team":"Cleveland Guardians","away_team":"Boston Red Sox","home_sp_id":677944,"away_sp_id":701719,"venue":"Progressive Field","park_run_factor":98.0,"weather":{"temp_f":72,"wind_mph":8,"wind_dir":"8 mph blowing In","blowing_out":false},"odds":{"home_ml":-121,"away_ml":112,"total":8.0,"over_price":-106,"under_price":-106},"game_status":"preview","home_score":0,"away_score":0,"current_inning":1,"inning_state":"Top 1st","outs":0,"home_sp":{"name":"Cecconi, Slade","mlbam_id":677944,"throws":null,"season":{"xera":4.71,"xba":0.269,"whiff_pct":0.164,"chase_pct":0.28,"k_pct":0.239,"bb_pct":null,"rv100":null,"era":5.18,"ip":null},"recent":{"k_pct":0.239,"bb_pct":0.06,"whiff_pct":0.164,"chase_pct":0.28,"starts_n":3},"last_start":{"deviation":0.69,"era_est":5.4,"ip":5.0},"trend_flags":[]},"away_sp":{"name":"Samaniego, Tyler","mlbam_id":701719,"throws":null,"season":{"xera":4.74,"xba":0.261,"whiff_pct":0.167,"chase_pct":0.172,"k_pct":null,"bb_pct":null,"rv100":null,"era":1.04,"ip":null},"recent":{},"last_start":{},"trend_flags":["Outperforming xERA: ERA (1.04) << xERA (4.74)"]},"home_lineup":[{"name":"Bazzana, Travis","mlbam_id":683953,"batting_order":1,"xwoba":0.354,"woba":0.386,"avg_ev":89.9,"hard_hit_pct":0.387,"k_pct":null,"bb_pct":null,"trend_flags":["Hot: 8H in last 5 games"]},{"name":"Ram\u00edrez, Jos\u00e9","mlbam_id":608070,"batting_order":2,"xwoba":0.366,"woba":0.326,"avg_ev":89.9,"hard_hit_pct":0.417,"k_pct":null,"bb_pct":null,"trend_flags":[]},{"name":"DeLauter, Chase","mlbam_id":800050,"batting_order":3,"xwoba":0.351,"woba":0.346,"avg_ev":89.8,"hard_hit_pct":0.391,"k_pct":null,"bb_pct":null,"trend_flags":[]},{"name":"Hoskins, Rhys","mlbam_id":656555,"batting_order":4,"xwoba":0.303,"woba":0.325,"avg_ev":88.5,"hard_hit_pct":0.457,"k_pct":null,"bb_pct":null,"trend_flags":[]},{"name":"Manzardo, Kyle","mlbam_id":700932,"batting_order":5,"xwoba":0.322,"woba":0.303,"avg_ev":89.4,"hard_hit_pct":0.43,"k_pct":null,"bb_pct":null,"trend_flags":[]},{"name":"Mart\u00ednez, Angel","mlbam_id":682657,"batting_order":6,"xwoba":0.306,"woba":0.324,"avg_ev":87.9,"hard_hit_pct":0.352,"k_pct":null,"bb_pct":null,"trend_flags":[]},{"name":"Schneemann, Daniel","mlbam_id":682177,"batting_order":7,"xwoba":0.32,"woba":0.319,"avg_ev":87.6,"hard_hit_pct":0.367,"k_pct":null,"bb_pct":null,"trend_flags":[]},{"name":"Bailey, Patrick","mlbam_id":672275,"batting_order":8,"xwoba":0.284,"woba":0.194,"avg_ev":90.3,"hard_hit_pct":0.38,"k_pct":null,"bb_pct":null,"trend_flags":[]},{"name":"Rocchio, Brayan","mlbam_id":677587,"batting_order":9,"xwoba":0.325,"woba":0.36,"avg_ev":86.6,"hard_hit_pct":0.333,"k_pct":null,"bb_pct":null,"trend_flags":["Hot: 6H in last 5 games"]}],"away_lineup":[{"name":"Duran, Jarren","mlbam_id":680776,"batting_order":1,"xwoba":0.308,"woba":0.296,"avg_ev":90.4,"hard_hit_pct":0.399,"k_pct":null,"bb_pct":null,"trend_flags":["Hot: 9H in last 5 games"]},{"name":"Rafaela, Ceddanne","mlbam_id":678882,"batting_order":2,"xwoba":0.305,"woba":0.35,"avg_ev":87.3,"hard_hit_pct":0.383,"k_pct":null,"bb_pct":null,"trend_flags":["Hot: 7H in last 5 games"]},{"name":"Abreu, Wilyer","mlbam_id":677800,"batting_order":3,"xwoba":0.346,"woba":0.346,"avg_ev":89.9,"hard_hit_pct":0.419,"k_pct":null,"bb_pct":null,"trend_flags":[]},{"name":"Contreras, Willson","mlbam_id":575929,"batting_order":4,"xwoba":0.397,"woba":0.392,"avg_ev":90.1,"hard_hit_pct":0.434,"k_pct":null,"bb_pct":null,"trend_flags":["Hot: 8H in last 5 games"]},{"name":"Yoshida, Masataka","mlbam_id":807799,"batting_order":5,"xwoba":0.308,"woba":0.323,"avg_ev":88.8,"hard_hit_pct":0.441,"k_pct":null,"bb_pct":null,"trend_flags":[]},{"name":"Gasper, Mickey","mlbam_id":681508,"batting_order":6,"xwoba":0.314,"woba":0.336,"avg_ev":null,"hard_hit_pct":null,"k_pct":null,"bb_pct":null,"trend_flags":[]},{"name":"Kiner-Falefa, Isiah","mlbam_id":643396,"batting_order":7,"xwoba":0.317,"woba":0.349,"avg_ev":84.5,"hard_hit_pct":0.255,"k_pct":null,"bb_pct":null,"trend_flags":["Hot: 6H in last 5 games"]},{"name":"Mayer, Marcelo","mlbam_id":691785,"batting_order":8,"xwoba":0.258,"woba":0.263,"avg_ev":87.1,"hard_hit_pct":0.39,"k_pct":null,"bb_pct":null,"trend_flags":[]},{"name":"Durbin, Caleb","mlbam_id":702332,"batting_order":9,"xwoba":0.265,"woba":0.233,"avg_ev":84.8,"hard_hit_pct":0.281,"k_pct":null,"bb_pct":null,"trend_flags":[]}],"lineup_status":"official","prediction":{"home_win_pct":0.5548,"away_win_pct":0.4452,"predicted_home_runs":4.0,"predicted_away_runs":4.0,"predicted_total":8.0,"narrative":"Cecconi's control issues (6.0% BB rate, last start +0.69 ERA deviation) create vulnerability against Boston's lineup despite modest park disadvantage, while Samaniego's extreme ERA-xERA disconnect (1.04 actual vs 4.74 projected) signals unsustainable performance that the model treats with appropriate skepticism. The pitcher score differential tilts slightly toward the visitor (-0.046), and Cleveland's marginal lineup advantage (+0.059) doesn't offset Samaniego's regression risk, making the model's 55.5% home lean conservative relative to the -121 Vegas price. Total of 8.0 aligns with model expectations, suggesting limited value on the over.","model_edge_ml":0.0176,"pitcher_score_diff":-0.0461,"pick_tier":null,"model_signals":{"pitcher_score_home":0.39,"pitcher_score_away":0.436,"lineup_score_home":0.451,"lineup_score_away":0.392,"comps_home_win_rate":0.6333,"comps_count":30,"park_modifier":-0.002,"weather_modifier":0.0,"rest_modifier":0.04,"home_rest_days":1,"away_rest_days":0,"bullpen_xera_home":null,"bullpen_xera_away":null,"bp_ip_last_3_home":null,"bp_ip_last_3_away":null,"last_start_dev_home":-0.91,"last_start_dev_away":null,"last_3_start_dev_home":-0.91,"last_3_start_dev_away":null,"last_start_pitches_home":null,"last_start_pitches_away":null,"umpire":"John Tumpane","consensus_suppressed":false}},"away_record":{"wins":23,"losses":32,"streak":"L1","l10_w":4,"l10_l":6},"home_record":{"wins":33,"losses":25,"streak":"W1","l10_w":7,"l10_l":3}},{"gamePk":822978,"game_time_utc":"2026-05-29T23:10:00Z","game_time_et":"7:10 PM ET","home_team":"Tampa Bay Rays","away_team":"Los Angeles Angels","home_sp_id":607259,"away_sp_id":700712,"venue":"Tropicana Field","park_run_factor":94.0,"weather":{"condition":"Dome"},"odds":{"home_ml":-156,"away_ml":143,"total":8.0,"over_price":101,"under_price":-113,"line_movement":{"ml_move":-0.022,"opening_home_ml":-174,"current_home_ml":-156}},"game_status":"preview","home_score":0,"away_score":0,"current_inning":1,"inning_state":"Top 1st","outs":0,"home_sp":{"name":"Martinez, Nick","mlbam_id":607259,"throws":null,"season":{"xera":4.26,"xba":0.275,"whiff_pct":0.177,"chase_pct":0.304,"k_pct":0.108,"bb_pct":null,"rv100":null,"era":1.51,"ip":null},"recent":{"k_pct":0.108,"bb_pct":0.027,"whiff_pct":0.177,"chase_pct":0.304,"starts_n":3},"last_start":{"deviation":-2.76,"era_est":1.5,"ip":6.0},"trend_flags":["Outperforming xERA: ERA (1.51) << xERA (4.26)"]},"away_sp":{"name":"Ure\u00f1a, Walbert","mlbam_id":700712,"throws":null,"season":{"xera":3.3,"xba":0.206,"whiff_pct":0.294,"chase_pct":0.309,"k_pct":0.209,"bb_pct":null,"rv100":null,"era":2.58,"ip":null},"recent":{"k_pct":0.209,"bb_pct":0.09,"whiff_pct":0.294,"chase_pct":0.309,"starts_n":3},"last_start":{"deviation":-1.5,"era_est":1.8,"ip":5.0},"trend_flags":[]},"home_lineup":[{"name":"D\u00edaz, Yandy","mlbam_id":650490,"batting_order":1,"xwoba":0.367,"woba":0.388,"avg_ev":90.5,"hard_hit_pct":0.451,"k_pct":null,"bb_pct":null,"trend_flags":[]},{"name":"Aranda, Jonathan","mlbam_id":666018,"batting_order":2,"xwoba":0.376,"woba":0.374,"avg_ev":90.7,"hard_hit_pct":0.461,"k_pct":null,"bb_pct":null,"trend_flags":["Hot: 9H in last 5 games"]},{"name":"Caminero, Junior","mlbam_id":691406,"batting_order":3,"xwoba":0.372,"woba":0.365,"avg_ev":92.4,"hard_hit_pct":0.467,"k_pct":null,"bb_pct":null,"trend_flags":[]},{"name":"Vilade, Ryan","mlbam_id":668723,"batting_order":4,"xwoba":0.32,"woba":0.372,"avg_ev":88.8,"hard_hit_pct":0.356,"k_pct":null,"bb_pct":null,"trend_flags":[]},{"name":"Simpson, Chandler","mlbam_id":802415,"batting_order":5,"xwoba":0.263,"woba":0.304,"avg_ev":84.4,"hard_hit_pct":0.165,"k_pct":null,"bb_pct":null,"trend_flags":["Hot: 8H in last 5 games"]},{"name":"Williamson, Ben","mlbam_id":810938,"batting_order":6,"xwoba":0.311,"woba":0.316,"avg_ev":89.4,"hard_hit_pct":0.393,"k_pct":null,"bb_pct":null,"trend_flags":[]},{"name":"Palacios, Richie","mlbam_id":680700,"batting_order":7,"xwoba":0.304,"woba":0.32,"avg_ev":87.2,"hard_hit_pct":0.276,"k_pct":null,"bb_pct":null,"trend_flags":[]},{"name":"Fortes, Nick","mlbam_id":663743,"batting_order":8,"xwoba":0.27,"woba":0.285,"avg_ev":87.2,"hard_hit_pct":0.435,"k_pct":null,"bb_pct":null,"trend_flags":[]},{"name":"Mullins, Cedric","mlbam_id":656775,"batting_order":9,"xwoba":0.244,"woba":0.245,"avg_ev":87.9,"hard_hit_pct":0.301,"k_pct":null,"bb_pct":null,"trend_flags":[]}],"away_lineup":[{"name":"Neto, Zach","mlbam_id":687263,"batting_order":1,"xwoba":0.328,"woba":0.345,"avg_ev":89.8,"hard_hit_pct":0.386,"k_pct":null,"bb_pct":null,"trend_flags":["Hot: 7H in last 5 games"]},{"name":"Trout, Mike","mlbam_id":545361,"batting_order":2,"xwoba":0.42,"woba":0.39,"avg_ev":91.2,"hard_hit_pct":0.486,"k_pct":null,"bb_pct":null,"trend_flags":[]},{"name":"Grissom, Vaughn","mlbam_id":687093,"batting_order":3,"xwoba":0.339,"woba":0.3,"avg_ev":90.9,"hard_hit_pct":0.48,"k_pct":null,"bb_pct":null,"trend_flags":[]},{"name":"Adell, Jo","mlbam_id":666176,"batting_order":4,"xwoba":0.335,"woba":0.301,"avg_ev":91.9,"hard_hit_pct":0.482,"k_pct":null,"bb_pct":null,"trend_flags":[]},{"name":"Meckler, Wade","mlbam_id":685133,"batting_order":5,"xwoba":0.401,"woba":0.383,"avg_ev":null,"hard_hit_pct":null,"k_pct":null,"bb_pct":null,"trend_flags":[]},{"name":"Peraza, Oswald","mlbam_id":672724,"batting_order":6,"xwoba":0.326,"woba":0.347,"avg_ev":86.4,"hard_hit_pct":0.321,"k_pct":null,"bb_pct":null,"trend_flags":[]},{"name":"Unknown","mlbam_id":663611,"batting_order":7,"xwoba":null,"woba":null,"avg_ev":null,"hard_hit_pct":null,"k_pct":null,"bb_pct":null,"trend_flags":[]},{"name":"O'Hoppe, Logan","mlbam_id":681351,"batting_order":8,"xwoba":0.278,"woba":0.262,"avg_ev":86.3,"hard_hit_pct":0.37,"k_pct":null,"bb_pct":null,"trend_flags":[]},{"name":"Siri, Jose","mlbam_id":642350,"batting_order":9,"xwoba":0.27,"woba":0.414,"avg_ev":null,"hard_hit_pct":null,"k_pct":null,"bb_pct":null,"trend_flags":[]}],"lineup_status":"official","prediction":{"home_win_pct":0.5372,"away_win_pct":0.4628,"predicted_home_runs":3.9,"predicted_away_runs":4.1,"predicted_total":8.0,"narrative":"Martinez carries a severe ERA-xERA gap (1.51 vs 4.26) suggesting significant negative regression risk, while Ure\u00f1a's superior peripherals (20.9% K-rate, 29.4% whiff%) and stronger xERA (3.30) present the more sustainable profile. The Angels' lineup edge (0.337 vs 0.314 xwOBA) combined with the model's pitcher score disadvantage (-0.139) tilts toward underdog value, though the model's 53.7% home win projection reflects that Martinez's recent performance still carries some predictive weight despite underlying metrics flagging vulnerability.","model_edge_ml":-0.0597,"pitcher_score_diff":-0.139,"pick_tier":null,"model_signals":{"pitcher_score_home":0.426,"pitcher_score_away":0.565,"lineup_score_home":0.378,"lineup_score_away":0.56,"comps_home_win_rate":0.5667,"comps_count":30,"park_modifier":-0.006,"weather_modifier":0.0,"rest_modifier":0.04,"home_rest_days":1,"away_rest_days":0,"bullpen_xera_home":null,"bullpen_xera_away":null,"bp_ip_last_3_home":null,"bp_ip_last_3_away":null,"last_start_dev_home":-2.79,"last_start_dev_away":-1.59,"last_3_start_dev_home":-2.79,"last_3_start_dev_away":-1.59,"last_start_pitches_home":null,"last_start_pitches_away":null,"umpire":"Lance Barrett","consensus_suppressed":false}},"away_record":{"wins":22,"losses":35,"streak":"W1","l10_w":6,"l10_l":4},"home_record":{"wins":34,"losses":19,"streak":"L4","l10_w":5,"l10_l":5}},{"gamePk":823623,"game_time_utc":"2026-05-29T23:10:00Z","game_time_et":"7:10 PM ET","home_team":"New York Mets","away_team":"Miami Marlins","home_sp_id":642547,"away_sp_id":676974,"venue":"Citi Field","park_run_factor":95.0,"weather":{"temp_f":70,"wind_mph":9,"wind_dir":"9 mph blowing Out","blowing_out":true},"odds":{"home_ml":-109,"away_ml":100,"total":7.5,"over_price":107,"under_price":-120},"game_status":"preview","home_score":0,"away_score":0,"current_inning":1,"inning_state":"Top 1st","outs":0,"home_sp":{"name":"Peralta, Freddy","mlbam_id":642547,"throws":null,"season":{"xera":3.5,"xba":0.224,"whiff_pct":0.197,"chase_pct":0.229,"k_pct":0.256,"bb_pct":null,"rv100":null,"era":3.52,"ip":null},"recent":{"k_pct":0.256,"bb_pct":0.115,"whiff_pct":0.197,"chase_pct":0.229,"starts_n":3},"last_start":{"deviation":1.64,"era_est":5.14,"ip":7.0},"trend_flags":[]},"away_sp":{"name":"Meyer, Max","mlbam_id":676974,"throws":null,"season":{"xera":3.79,"xba":0.233,"whiff_pct":0.318,"chase_pct":0.327,"k_pct":0.311,"bb_pct":null,"rv100":null,"era":2.52,"ip":null},"recent":{"k_pct":0.311,"bb_pct":0.095,"whiff_pct":0.318,"chase_pct":0.327,"starts_n":3},"last_start":{"deviation":-3.0,"era_est":0.0,"ip":7.0},"trend_flags":["Outperforming xERA: ERA (2.52) << xERA (3.79)"]},"home_lineup":[{"name":"Benge, Carson","mlbam_id":701807,"batting_order":1,"xwoba":0.333,"woba":0.294,"avg_ev":89.7,"hard_hit_pct":0.434,"k_pct":null,"bb_pct":null,"trend_flags":[]},{"name":"Bichette, Bo","mlbam_id":666182,"batting_order":2,"xwoba":0.329,"woba":0.267,"avg_ev":90.9,"hard_hit_pct":0.449,"k_pct":null,"bb_pct":null,"trend_flags":[]},{"name":"Soto, Juan","mlbam_id":665742,"batting_order":3,"xwoba":0.415,"woba":0.417,"avg_ev":93.1,"hard_hit_pct":0.504,"k_pct":null,"bb_pct":null,"trend_flags":[]},{"name":"Young, Jared","mlbam_id":676724,"batting_order":4,"xwoba":0.377,"woba":0.372,"avg_ev":null,"hard_hit_pct":null,"k_pct":null,"bb_pct":null,"trend_flags":[]},{"name":"Ewing, A.J.","mlbam_id":805999,"batting_order":5,"xwoba":0.342,"woba":0.32,"avg_ev":null,"hard_hit_pct":null,"k_pct":null,"bb_pct":null,"trend_flags":[]},{"name":"Vientos, Mark","mlbam_id":668901,"batting_order":6,"xwoba":0.323,"woba":0.282,"avg_ev":90.6,"hard_hit_pct":0.466,"k_pct":null,"bb_pct":null,"trend_flags":[]},{"name":"Baty, Brett","mlbam_id":683146,"batting_order":7,"xwoba":0.313,"woba":0.295,"avg_ev":89.7,"hard_hit_pct":0.388,"k_pct":null,"bb_pct":null,"trend_flags":[]},{"name":"Semien, Marcus","mlbam_id":543760,"batting_order":8,"xwoba":0.308,"woba":0.257,"avg_ev":85.9,"hard_hit_pct":0.34,"k_pct":null,"bb_pct":null,"trend_flags":[]},{"name":"Torrens, Luis","mlbam_id":620443,"batting_order":9,"xwoba":0.259,"woba":0.253,"avg_ev":89.0,"hard_hit_pct":0.426,"k_pct":null,"bb_pct":null,"trend_flags":[]}],"away_lineup":[],"lineup_status":"official","prediction":{"home_win_pct":0.467,"away_win_pct":0.533,"predicted_home_runs":3.7,"predicted_away_runs":3.7,"predicted_total":7.4,"narrative":"Meyer's elite 31.1% strikeout rate and 31.8% whiff percentage anchor Miami's pitching advantage, while his significant ERA outperformance versus xERA (2.52 vs 3.79) suggests underlying sustainability despite last start's regression. Peralta's elevated 11.5% walk rate and modest whiff numbers expose vulnerabilities that Meyer's command profile targets, though the outfield wind and neutral pitcher score differential (-0.048) limit the magnitude of any edge. The model's 46.7% home win probability falls materially below Vegas's implied 52.4% Mets win probability, suggesting value on Miami despite playing on the road.","model_edge_ml":-0.0435,"pitcher_score_diff":-0.0482,"pick_tier":null,"model_signals":{"pitcher_score_home":0.513,"pitcher_score_away":0.561,"lineup_score_home":0.531,"lineup_score_away":0.5,"comps_home_win_rate":0.4333,"comps_count":30,"park_modifier":-0.005,"weather_modifier":0.0,"rest_modifier":0.0,"home_rest_days":1,"away_rest_days":1,"bullpen_xera_home":null,"bullpen_xera_away":null,"bp_ip_last_3_home":null,"bp_ip_last_3_away":null,"last_start_dev_home":1.29,"last_start_dev_away":-1.8,"last_3_start_dev_home":1.29,"last_3_start_dev_away":-1.8,"last_start_pitches_home":null,"last_start_pitches_away":null,"umpire":"Will Little","consensus_suppressed":false}},"away_record":{"wins":26,"losses":31,"streak":"L2","l10_w":5,"l10_l":5},"home_record":{"wins":23,"losses":33,"streak":"W1","l10_w":3,"l10_l":7}},{"gamePk":823055,"game_time_utc":"2026-05-29T23:15:00Z","game_time_et":"7:15 PM ET","home_team":"St. Louis Cardinals","away_team":"Chicago Cubs","home_sp_id":669467,"away_sp_id":684007,"venue":"Busch Stadium","park_run_factor":96.0,"weather":{"temp_f":81,"wind_mph":6,"wind_dir":"6 mph blowing Out","blowing_out":true},"odds":{"home_ml":114,"away_ml":-124,"total":7.5,"over_price":-111,"under_price":-101,"line_movement":{"total_move":-0.5,"opening_total":8.0,"current_total":7.5}},"game_status":"preview","home_score":0,"away_score":0,"current_inning":1,"inning_state":"Top 1st","outs":0,"home_sp":{"name":"Pallante, Andre","mlbam_id":669467,"throws":null,"season":{"xera":3.73,"xba":0.23,"whiff_pct":0.216,"chase_pct":0.315,"k_pct":0.206,"bb_pct":null,"rv100":null,"era":3.76,"ip":null},"recent":{"k_pct":0.206,"bb_pct":0.059,"whiff_pct":0.216,"chase_pct":0.315,"starts_n":3},"last_start":{"deviation":-2.23,"era_est":1.5,"ip":6.0},"trend_flags":[]},"away_sp":{"name":"Imanaga, Shota","mlbam_id":684007,"throws":null,"season":{"xera":3.4,"xba":0.228,"whiff_pct":0.246,"chase_pct":0.324,"k_pct":0.189,"bb_pct":null,"rv100":null,"era":4.04,"ip":null},"recent":{"k_pct":0.189,"bb_pct":0.054,"whiff_pct":0.246,"chase_pct":0.324,"starts_n":3},"last_start":{"deviation":3.0,"era_est":10.5,"ip":6.0},"trend_flags":[]},"home_lineup":[{"name":"Wetherholt, JJ","mlbam_id":802139,"batting_order":1,"xwoba":0.356,"woba":0.336,"avg_ev":90.4,"hard_hit_pct":0.46,"k_pct":null,"bb_pct":null,"trend_flags":[]},{"name":"Herrera, Iv\u00e1n","mlbam_id":671056,"batting_order":2,"xwoba":0.364,"woba":0.363,"avg_ev":89.5,"hard_hit_pct":0.425,"k_pct":null,"bb_pct":null,"trend_flags":[]},{"name":"Walker, Jordan","mlbam_id":691023,"batting_order":3,"xwoba":0.383,"woba":0.409,"avg_ev":94.2,"hard_hit_pct":0.52,"k_pct":null,"bb_pct":null,"trend_flags":["Hot: 7H in last 5 games"]},{"name":"Unknown","mlbam_id":676369,"batting_order":4,"xwoba":null,"woba":null,"avg_ev":null,"hard_hit_pct":null,"k_pct":null,"bb_pct":null,"trend_flags":[]},{"name":"Burleson, Alec","mlbam_id":676475,"batting_order":5,"xwoba":0.382,"woba":0.35,"avg_ev":91.3,"hard_hit_pct":0.474,"k_pct":null,"bb_pct":null,"trend_flags":[]},{"name":"Winn, Masyn","mlbam_id":691026,"batting_order":6,"xwoba":0.296,"woba":0.285,"avg_ev":86.8,"hard_hit_pct":0.293,"k_pct":null,"bb_pct":null,"trend_flags":[]},{"name":"Ferm\u00edn, Jos\u00e9","mlbam_id":665877,"batting_order":7,"xwoba":0.249,"woba":0.292,"avg_ev":85.2,"hard_hit_pct":0.32,"k_pct":null,"bb_pct":null,"trend_flags":[]},{"name":"Saggese, Thomas","mlbam_id":695336,"batting_order":8,"xwoba":0.258,"woba":0.191,"avg_ev":null,"hard_hit_pct":null,"k_pct":null,"bb_pct":null,"trend_flags":[]},{"name":"Scott II, Victor","mlbam_id":687363,"batting_order":9,"xwoba":0.263,"woba":0.24,"avg_ev":87.5,"hard_hit_pct":0.267,"k_pct":null,"bb_pct":null,"trend_flags":[]}],"away_lineup":[],"lineup_status":"official","prediction":{"home_win_pct":0.4994,"away_win_pct":0.5006,"predicted_home_runs":3.7,"predicted_away_runs":3.8,"predicted_total":7.5,"narrative":"Pallante's superior command metrics (5.9% BB rate, 21.6% whiff) paired with Busch Stadium's suppressive run environment (96 park factor) anchor the Cardinals' slight pitching advantage, though the edge is marginal at +0.015. Imanaga's underlying peripherals (3.40 xERA vs 4.04 actual) suggest positive regression risk, but his +3.00 ERA deviation in his last start signals recent volatility that could persist against a Cubs lineup that grades slightly negative (-0.070 vs STL). Model projects near-even win probability (49.9%) with no notable edge vs Vegas pricing.","model_edge_ml":0.0417,"pitcher_score_diff":0.0147,"pick_tier":null,"model_signals":{"pitcher_score_home":0.512,"pitcher_score_away":0.497,"lineup_score_home":0.43,"lineup_score_away":0.5,"comps_home_win_rate":0.6333,"comps_count":30,"park_modifier":-0.004,"weather_modifier":0.1,"rest_modifier":0.04,"home_rest_days":1,"away_rest_days":0,"bullpen_xera_home":null,"bullpen_xera_away":null,"bp_ip_last_3_home":null,"bp_ip_last_3_away":null,"last_start_dev_home":-1.47,"last_start_dev_away":2.23,"last_3_start_dev_home":-1.47,"last_3_start_dev_away":2.23,"last_start_pitches_home":null,"last_start_pitches_away":null,"umpire":"Paul Clemons","consensus_suppressed":false}},"away_record":{"wins":31,"losses":26,"streak":"W2","l10_w":2,"l10_l":8},"home_record":{"wins":29,"losses":25,"streak":"L4","l10_w":3,"l10_l":7}},{"gamePk":824594,"game_time_utc":"2026-05-29T23:40:00Z","game_time_et":"7:40 PM ET","home_team":"Chicago White Sox","away_team":"Detroit Tigers","home_sp_id":607200,"away_sp_id":675512,"venue":"Rate Field","park_run_factor":102.0,"weather":{},"odds":{"home_ml":102,"away_ml":-110,"total":8.5,"over_price":-116,"under_price":103},"game_status":"preview","home_score":0,"away_score":0,"current_inning":1,"inning_state":"Top 1st","outs":0,"home_sp":{"name":"Fedde, Erick","mlbam_id":607200,"throws":null,"season":{"xera":4.68,"xba":0.257,"whiff_pct":0.13,"chase_pct":0.22,"k_pct":0.113,"bb_pct":null,"rv100":null,"era":5.47,"ip":null},"recent":{"k_pct":0.113,"bb_pct":0.113,"whiff_pct":0.13,"chase_pct":0.22,"starts_n":3},"last_start":{"deviation":3.0,"era_est":12.0,"ip":3.0},"trend_flags":["Regression candidate: ERA (5.47) >> xERA (4.68)"]},"away_sp":{"name":"Melton, Troy","mlbam_id":675512,"throws":null,"season":{"xera":5.77,"xba":0.283,"whiff_pct":0.179,"chase_pct":0.273,"k_pct":0.136,"bb_pct":null,"rv100":null,"era":1.59,"ip":null},"recent":{"k_pct":0.136,"bb_pct":0.136,"whiff_pct":0.179,"chase_pct":0.273,"starts_n":1},"last_start":{"deviation":-3.0,"era_est":1.72,"ip":5.2},"trend_flags":["Outperforming xERA: ERA (1.59) << xERA (5.77)"]},"home_lineup":[{"name":"Antonacci, Sam","mlbam_id":803011,"batting_order":1,"xwoba":0.383,"woba":0.351,"avg_ev":87.6,"hard_hit_pct":0.364,"k_pct":null,"bb_pct":null,"trend_flags":["Hot: 6H in last 5 games"]},{"name":"Murakami, Munetaka","mlbam_id":808959,"batting_order":2,"xwoba":0.382,"woba":0.405,"avg_ev":94.1,"hard_hit_pct":0.583,"k_pct":null,"bb_pct":null,"trend_flags":[]},{"name":"Vargas, Miguel","mlbam_id":678246,"batting_order":3,"xwoba":0.389,"woba":0.367,"avg_ev":90.1,"hard_hit_pct":0.458,"k_pct":null,"bb_pct":null,"trend_flags":[]},{"name":"Montgomery, Colson","mlbam_id":695657,"batting_order":4,"xwoba":0.329,"woba":0.35,"avg_ev":90.1,"hard_hit_pct":0.44,"k_pct":null,"bb_pct":null,"trend_flags":["Hot: 6H in last 5 games"]},{"name":"Meidroth, Chase","mlbam_id":805367,"batting_order":5,"xwoba":0.301,"woba":0.329,"avg_ev":87.6,"hard_hit_pct":0.377,"k_pct":null,"bb_pct":null,"trend_flags":["Hot: 7H in last 5 games"]},{"name":"Benintendi, Andrew","mlbam_id":643217,"batting_order":6,"xwoba":0.305,"woba":0.28,"avg_ev":88.7,"hard_hit_pct":0.469,"k_pct":null,"bb_pct":null,"trend_flags":[]},{"name":"Peters, Tristan","mlbam_id":671976,"batting_order":7,"xwoba":0.291,"woba":0.328,"avg_ev":87.3,"hard_hit_pct":0.25,"k_pct":null,"bb_pct":null,"trend_flags":[]},{"name":"Nishida, Rikuu","mlbam_id":807747,"batting_order":8,"xwoba":0.145,"woba":0.2,"avg_ev":null,"hard_hit_pct":null,"k_pct":null,"bb_pct":null,"trend_flags":[]},{"name":"Romo, Drew","mlbam_id":691011,"batting_order":9,"xwoba":0.314,"woba":0.35,"avg_ev":null,"hard_hit_pct":null,"k_pct":null,"bb_pct":null,"trend_flags":[]}],"away_lineup":[],"lineup_status":"official","prediction":{"home_win_pct":0.4075,"away_win_pct":0.5925,"predicted_home_runs":4.2,"predicted_away_runs":4.2,"predicted_total":8.4,"narrative":"Melton's 1.59 ERA sits 5.18 runs below his 5.77 xERA, signaling unsustainable run prevention and regression risk against a White Sox lineup that has solid offensive metrics. Fedde's 5.47 ERA exceeds his 4.68 xERA by 0.79 runs, though his recent +3.00 deviation suggests control issues are real; combined with a neutral pitcher advantage (-0.061), the model leans toward undervaluing Detroit's true pitching edge. The model's 40.8% home win probability sits modestly below the implied 49.5% from Vegas (+102), with the total projection (8.4) slightly under the market (8.5), indicating value on the away side or under positioning.","model_edge_ml":-0.0784,"pitcher_score_diff":-0.0612,"pick_tier":null,"model_signals":{"pitcher_score_home":0.295,"pitcher_score_away":0.356,"lineup_score_home":0.477,"lineup_score_away":0.5,"comps_home_win_rate":0.6667,"comps_count":30,"park_modifier":0.002,"weather_modifier":0.0,"rest_modifier":0.0,"home_rest_days":0,"away_rest_days":0,"bullpen_xera_home":null,"bullpen_xera_away":null,"bp_ip_last_3_home":null,"bp_ip_last_3_away":null,"last_start_dev_home":1.78,"last_start_dev_away":-3.0,"last_3_start_dev_home":1.78,"last_3_start_dev_away":-3.0,"last_start_pitches_home":null,"last_start_pitches_away":null,"umpire":"Hunter Wendelstedt","consensus_suppressed":false}},"away_record":{"wins":22,"losses":35,"streak":"L1","l10_w":2,"l10_l":8},"home_record":{"wins":29,"losses":27,"streak":"W2","l10_w":5,"l10_l":5}},{"gamePk":822894,"game_time_utc":"2026-05-30T00:05:00Z","game_time_et":"8:05 PM ET","home_team":"Texas Rangers","away_team":"Kansas City Royals","home_sp_id":669022,"away_sp_id":663568,"venue":"Globe Life Field","park_run_factor":106.0,"weather":{"temp_f":91,"wind_mph":8,"wind_dir":"8 mph blowing Out","blowing_out":true},"odds":{"home_ml":-125,"away_ml":115,"total":7.5,"over_price":103,"under_price":-116},"game_status":"preview","home_score":0,"away_score":0,"current_inning":1,"inning_state":"Top 1st","outs":0,"home_sp":{"name":"Gore, MacKenzie","mlbam_id":669022,"throws":null,"season":{"xera":3.81,"xba":0.225,"whiff_pct":0.257,"chase_pct":0.344,"k_pct":0.246,"bb_pct":null,"rv100":null,"era":4.42,"ip":null},"recent":{"k_pct":0.246,"bb_pct":0.088,"whiff_pct":0.257,"chase_pct":0.344,"starts_n":3},"last_start":{"deviation":-2.31,"era_est":1.5,"ip":6.0},"trend_flags":[]},"away_sp":{"name":"Kolek, Stephen","mlbam_id":663568,"throws":null,"season":{"xera":3.14,"xba":0.244,"whiff_pct":0.185,"chase_pct":0.269,"k_pct":0.143,"bb_pct":null,"rv100":null,"era":2.77,"ip":null},"recent":{"k_pct":0.143,"bb_pct":0.065,"whiff_pct":0.185,"chase_pct":0.269,"starts_n":3},"last_start":{"deviation":-3.0,"era_est":0.0,"ip":9.0},"trend_flags":[]},"home_lineup":[],"away_lineup":[],"lineup_status":"official","prediction":{"home_win_pct":0.5379,"away_win_pct":0.4621,"predicted_home_runs":3.8,"predicted_away_runs":3.8,"predicted_total":7.6,"narrative":"Gore's recent ERA deviation of -2.31 suggests significant positive regression risk, while Kolek's superior xERA (3.14 vs 3.81) and lower walk rate provide the visitor with a genuine pitching advantage despite home field context. The model's modest home lean (53.8%) reflects near-parity in pitcher value and lineup composition, with Vegas alignment indicating the public correctly prices this matchup as a coin flip where the -125 home price slightly overcompensates for Gore's volatility and Globe Life's park factors (106 run environment).","model_edge_ml":-0.0064,"pitcher_score_diff":0.0073,"pick_tier":null,"model_signals":{"pitcher_score_home":0.515,"pitcher_score_away":0.507,"lineup_score_home":0.5,"lineup_score_away":0.5,"comps_home_win_rate":0.2667,"comps_count":30,"park_modifier":0.006,"weather_modifier":0.2,"rest_modifier":-0.04,"home_rest_days":0,"away_rest_days":1,"bullpen_xera_home":null,"bullpen_xera_away":null,"bp_ip_last_3_home":null,"bp_ip_last_3_away":null,"last_start_dev_home":-0.79,"last_start_dev_away":-1.8,"last_3_start_dev_home":-0.79,"last_3_start_dev_away":-1.8,"last_start_pitches_home":null,"last_start_pitches_away":null,"umpire":null,"consensus_suppressed":true}},"away_record":{"wins":22,"losses":34,"streak":"L3","l10_w":3,"l10_l":7},"home_record":{"wins":25,"losses":31,"streak":"L2","l10_w":3,"l10_l":7}},{"gamePk":824191,"game_time_utc":"2026-05-30T00:10:00Z","game_time_et":"8:10 PM ET","home_team":"Houston Astros","away_team":"Milwaukee Brewers","home_sp_id":678906,"away_sp_id":689441,"venue":"Daikin Park","park_run_factor":100.0,"weather":{},"odds":{"home_ml":107,"away_ml":-116,"total":8.5,"over_price":101,"under_price":-113},"game_status":"preview","home_score":0,"away_score":0,"current_inning":1,"inning_state":"Top 1st","outs":0,"home_sp":{"name":"Teng, Kai-Wei","mlbam_id":678906,"throws":null,"season":{"xera":3.55,"xba":0.226,"whiff_pct":0.291,"chase_pct":0.241,"k_pct":0.241,"bb_pct":null,"rv100":null,"era":2.19,"ip":null},"recent":{"k_pct":0.241,"bb_pct":0.138,"whiff_pct":0.291,"chase_pct":0.241,"starts_n":3},"last_start":{"deviation":-3.0,"era_est":0.0,"ip":6.0},"trend_flags":["Outperforming xERA: ERA (2.19) << xERA (3.55)"]},"away_sp":{"name":"Crow, Coleman","mlbam_id":689441,"throws":null,"season":{"xera":3.28,"xba":0.241,"whiff_pct":0.243,"chase_pct":0.4,"k_pct":0.15,"bb_pct":null,"rv100":null,"era":2.61,"ip":null},"recent":{"k_pct":0.15,"bb_pct":0.0,"whiff_pct":0.243,"chase_pct":0.4,"starts_n":1},"last_start":{"deviation":-1.48,"era_est":1.8,"ip":5.0},"trend_flags":[]},"home_lineup":[],"away_lineup":[],"lineup_status":"official","prediction":{"home_win_pct":0.472,"away_win_pct":0.528,"predicted_home_runs":4.2,"predicted_away_runs":4.2,"predicted_total":8.4,"narrative":"Teng's 136-point ERA-to-xERA gap signals significant positive regression risk, with his 2.19 ERA backed by underlying metrics (3.55 xERA, 13.8% BB rate) that suggest recent outperformance rather than sustainable dominance. Crow's more reliable peripherals (3.28 xERA, 15.0% K%) and steadier recent form create a marginal pitcher advantage for Milwaukee despite the model's -0.035 score differential. With lineups TBD and the model implying an 8.4 total versus Vegas 8.5 (minimal edge), the key risk is Teng reverting toward xERA\u2014favoring the away side if sharp action emerges pre-game.","model_edge_ml":-0.0016,"pitcher_score_diff":-0.0349,"pick_tier":null,"model_signals":{"pitcher_score_home":0.548,"pitcher_score_away":0.583,"lineup_score_home":0.5,"lineup_score_away":0.5,"comps_home_win_rate":0.6,"comps_count":30,"park_modifier":0.0,"weather_modifier":0.0,"rest_modifier":-0.04,"home_rest_days":0,"away_rest_days":1,"bullpen_xera_home":null,"bullpen_xera_away":null,"bp_ip_last_3_home":null,"bp_ip_last_3_away":null,"last_start_dev_home":-1.8,"last_start_dev_away":-0.83,"last_3_start_dev_home":-1.8,"last_3_start_dev_away":-0.83,"last_start_pitches_home":null,"last_start_pitches_away":null,"umpire":null,"consensus_suppressed":false}},"away_record":{"wins":33,"losses":20,"streak":"W3","l10_w":7,"l10_l":3},"home_record":{"wins":26,"losses":32,"streak":"W2","l10_w":7,"l10_l":3}},{"gamePk":824353,"game_time_utc":"2026-05-30T00:40:00Z","game_time_et":"8:40 PM ET","home_team":"Colorado Rockies","away_team":"San Francisco Giants","home_sp_id":547179,"away_sp_id":657277,"venue":"Coors Field","park_run_factor":118.0,"weather":{"temp_f":78,"wind_mph":5,"wind_dir":"5 mph blowing In","blowing_out":false},"odds":{"home_ml":130,"away_ml":-142,"total":10.5,"over_price":-115,"under_price":102,"line_movement":{"ml_move":0.032,"opening_home_ml":148,"current_home_ml":130}},"game_status":"preview","home_score":null,"away_score":null,"current_inning":null,"inning_state":null,"outs":null,"home_sp":{"name":"Lorenzen, Michael","mlbam_id":547179,"throws":null,"season":{"xera":5.88,"xba":0.314,"whiff_pct":0.167,"chase_pct":0.279,"k_pct":0.211,"bb_pct":null,"rv100":null,"era":7.21,"ip":null},"recent":{"k_pct":0.211,"bb_pct":0.085,"whiff_pct":0.167,"chase_pct":0.279,"starts_n":3},"last_start":{"deviation":3.0,"era_est":9.0,"ip":5.0},"trend_flags":["Regression candidate: ERA (7.21) >> xERA (5.88)"]},"away_sp":{"name":"Webb, Logan","mlbam_id":657277,"throws":null,"season":{"xera":4.56,"xba":0.28,"whiff_pct":null,"chase_pct":null,"k_pct":null,"bb_pct":null,"rv100":null,"era":5.06,"ip":null},"recent":{},"last_start":{"deviation":3.0,"era_est":13.5,"ip":4.0},"trend_flags":[]},"home_lineup":[],"away_lineup":[],"lineup_status":"official","prediction":{"home_win_pct":0.369,"away_win_pct":0.631,"predicted_home_runs":5.3,"predicted_away_runs":5.4,"predicted_total":10.7,"narrative":"Lorenzen's 7.21 ERA masks a more sustainable 5.88 xERA, suggesting regression upward from recent underperformance, but Coors Field's 118 run factor and Webb's modest 4.56 xERA create a ceiling on Giants scoring that aligns with the model's 10.7 total projection slightly above Vegas 10.5. The model's 36.9% home win probability reflects a -0.172 pitcher score disadvantage that Webb's superior command (8.5% BB% vs Lorenzen's baseline) accentuates, leaving Colorado undervalued at +130 despite their home park advantage and Lorenzen's ERA rebound potential.","model_edge_ml":-0.0566,"pitcher_score_diff":-0.1716,"pick_tier":null,"model_signals":{"pitcher_score_home":0.313,"pitcher_score_away":0.485,"lineup_score_home":0.5,"lineup_score_away":0.5,"comps_home_win_rate":0.4333,"comps_count":30,"park_modifier":0.018,"weather_modifier":0.0,"rest_modifier":0.0,"home_rest_days":1,"away_rest_days":1,"bullpen_xera_home":null,"bullpen_xera_away":null,"bp_ip_last_3_home":null,"bp_ip_last_3_away":null,"last_start_dev_home":1.94,"last_start_dev_away":0.46,"last_3_start_dev_home":1.94,"last_3_start_dev_away":0.46,"last_start_pitches_home":null,"last_start_pitches_away":null,"umpire":null,"consensus_suppressed":false}},"away_record":{"wins":22,"losses":34,"streak":"L3","l10_w":3,"l10_l":7},"home_record":{"wins":20,"losses":37,"streak":"L5","l10_w":2,"l10_l":8}},{"gamePk":825002,"game_time_utc":"2026-05-30T01:40:00Z","game_time_et":"9:40 PM ET","home_team":"Athletics","away_team":"New York Yankees","home_sp_id":622663,"away_sp_id":607074,"venue":"Sutter Health Park","park_run_factor":100.0,"weather":{"temp_f":73,"wind_mph":2,"wind_dir":"2 mph blowing In","blowing_out":false},"odds":{"home_ml":122,"away_ml":-133,"total":9.5,"over_price":-105,"under_price":-107,"line_movement":{"total_move":-0.5,"opening_total":10.0,"current_total":9.5,"ml_move":0.021,"opening_home_ml":132,"current_home_ml":122}},"game_status":"preview","home_score":null,"away_score":null,"current_inning":null,"inning_state":null,"outs":null,"home_sp":{"name":"Severino, Luis","mlbam_id":622663,"throws":null,"season":{"xera":4.09,"xba":0.231,"whiff_pct":0.195,"chase_pct":0.401,"k_pct":0.269,"bb_pct":null,"rv100":null,"era":4.23,"ip":null},"recent":{"k_pct":0.269,"bb_pct":0.077,"whiff_pct":0.195,"chase_pct":0.401,"starts_n":3},"last_start":{"deviation":-1.52,"era_est":2.57,"ip":7.0},"trend_flags":[]},"away_sp":{"name":"Rod\u00f3n, Carlos","mlbam_id":607074,"throws":null,"season":{"xera":2.96,"xba":0.153,"whiff_pct":0.274,"chase_pct":0.312,"k_pct":0.288,"bb_pct":null,"rv100":null,"era":4.15,"ip":null},"recent":{"k_pct":0.288,"bb_pct":0.186,"whiff_pct":0.274,"chase_pct":0.312,"starts_n":3},"last_start":{"deviation":-1.16,"era_est":1.8,"ip":5.0},"trend_flags":["Regression candidate: ERA (4.15) >> xERA (2.96)"]},"home_lineup":[],"away_lineup":[],"lineup_status":"official","prediction":{"home_win_pct":0.4265,"away_win_pct":0.5735,"predicted_home_runs":4.6,"predicted_away_runs":4.7,"predicted_total":9.3,"narrative":"Rod\u00f3n's 1.19-run ERA-to-xERA gap signals meaningful positive regression potential, and his elite 28.8% K-rate with 27.4% whiff rate provides strong strikeout leverage against a Yankees lineup that hasn't been posted. The model's predicted total of 9.3 sits below Vegas's 9.5, suggesting under value, though the pitcher matchup nearly balances (Rod\u00f3n's xERA advantage offset by Severino's marginally better recent form, which shows a -1.52 ERA deviation last time out). Lineups TBD creates execution uncertainty, and Rod\u00f3n's elevated 18.6% walk rate requires discipline to avoid self-inflicted damage in a close matchup where the model gives the Yankees a modest edge despite near-neutral pitcher scoring.","model_edge_ml":-0.0146,"pitcher_score_diff":-0.0982,"pick_tier":null,"model_signals":{"pitcher_score_home":0.529,"pitcher_score_away":0.627,"lineup_score_home":0.5,"lineup_score_away":0.5,"comps_home_win_rate":0.6,"comps_count":30,"park_modifier":0.0,"weather_modifier":0.0,"rest_modifier":0.0,"home_rest_days":1,"away_rest_days":1,"bullpen_xera_home":null,"bullpen_xera_away":null,"bp_ip_last_3_home":null,"bp_ip_last_3_away":null,"last_start_dev_home":0.03,"last_start_dev_away":0.81,"last_3_start_dev_home":0.03,"last_3_start_dev_away":0.81,"last_start_pitches_home":null,"last_start_pitches_away":null,"umpire":null,"consensus_suppressed":false}},"away_record":{"wins":34,"losses":22,"streak":"W4","l10_w":6,"l10_l":4},"home_record":{"wins":27,"losses":29,"streak":"L3","l10_w":4,"l10_l":6}},{"gamePk":823135,"game_time_utc":"2026-05-30T02:10:00Z","game_time_et":"10:10 PM ET","home_team":"Seattle Mariners","away_team":"Arizona Diamondbacks","home_sp_id":669923,"away_sp_id":668678,"venue":"T-Mobile Park","park_run_factor":95.0,"weather":{"temp_f":51,"wind_mph":5,"wind_dir":"5 mph blowing Out","blowing_out":true},"odds":{"home_ml":-133,"away_ml":123,"total":7.0,"over_price":-115,"under_price":102,"line_movement":{"ml_move":-0.021,"opening_home_ml":-147,"current_home_ml":-133}},"game_status":"preview","home_score":null,"away_score":null,"current_inning":null,"inning_state":null,"outs":null,"home_sp":{"name":"Kirby, George","mlbam_id":669923,"throws":null,"season":{"xera":3.35,"xba":0.246,"whiff_pct":0.228,"chase_pct":0.354,"k_pct":0.216,"bb_pct":null,"rv100":null,"era":3.54,"ip":null},"recent":{"k_pct":0.216,"bb_pct":0.054,"whiff_pct":0.228,"chase_pct":0.354,"starts_n":3},"last_start":{"deviation":1.15,"era_est":4.5,"ip":6.0},"trend_flags":[]},"away_sp":{"name":"Gallen, Zac","mlbam_id":668678,"throws":null,"season":{"xera":4.87,"xba":0.285,"whiff_pct":0.195,"chase_pct":0.333,"k_pct":0.211,"bb_pct":null,"rv100":null,"era":4.8,"ip":null},"recent":{"k_pct":0.211,"bb_pct":0.07,"whiff_pct":0.195,"chase_pct":0.333,"starts_n":3},"last_start":{"deviation":0.41,"era_est":5.28,"ip":5.1},"trend_flags":[]},"home_lineup":[],"away_lineup":[],"lineup_status":"tbd","prediction":{"home_win_pct":0.5515,"away_win_pct":0.4485,"predicted_home_runs":3.5,"predicted_away_runs":3.4,"predicted_total":6.9,"narrative":"Kirby's superior peripherals (3.35 xERA, 22.8% whiff rate) versus Gallen's elevated ERA and walk rate (7.0% BB%) anchor the model's 55.1% home lean, with a pitcher score differential of +0.174 driving modest edge over Vegas's -133 consensus. Cold conditions (51\u00b0F) at a slightly pitcher-friendly park (95 run factor) suppress run expectations to 6.9 total, aligning with Vegas's 7.0 line and dampening the model's offensive signals. Gallen's last start showed minor degradation (+0.41 ERA deviation), while Kirby posted a larger miss (+1.15), warranting close monitoring of recent form before lineups post.","model_edge_ml":-0.0085,"pitcher_score_diff":0.1738,"pick_tier":null,"model_signals":{"pitcher_score_home":0.585,"pitcher_score_away":0.411,"lineup_score_home":0.5,"lineup_score_away":0.5,"comps_home_win_rate":0.5,"comps_count":30,"park_modifier":-0.005,"weather_modifier":-0.15,"rest_modifier":0.0,"home_rest_days":1,"away_rest_days":1,"bullpen_xera_home":null,"bullpen_xera_away":null,"bp_ip_last_3_home":null,"bp_ip_last_3_away":null,"last_start_dev_home":1.16,"last_start_dev_away":0.25,"last_3_start_dev_home":1.16,"last_3_start_dev_away":0.25,"last_start_pitches_home":null,"last_start_pitches_away":null,"umpire":null,"consensus_suppressed":true}},"away_record":{"wins":31,"losses":24,"streak":"W5","l10_w":9,"l10_l":1},"home_record":{"wins":28,"losses":29,"streak":"W3","l10_w":6,"l10_l":4}},{"gamePk":823946,"game_time_utc":"2026-05-30T02:15:00Z","game_time_et":"10:15 PM ET","home_team":"Los Angeles Dodgers","away_team":"Philadelphia Phillies","home_sp_id":680736,"away_sp_id":554430,"venue":"UNIQLO Field at Dodger Stadium","park_run_factor":97.0,"weather":{},"odds":{"home_ml":-113,"away_ml":105,"total":8.0,"over_price":-109,"under_price":-103},"game_status":"preview","home_score":null,"away_score":null,"current_inning":null,"inning_state":null,"outs":null,"home_sp":{"name":"Wrobleski, Justin","mlbam_id":680736,"throws":null,"season":{"xera":4.09,"xba":0.265,"whiff_pct":0.193,"chase_pct":0.312,"k_pct":0.191,"bb_pct":null,"rv100":null,"era":3.07,"ip":null},"recent":{"k_pct":0.19,"bb_pct":0.048,"whiff_pct":0.193,"chase_pct":0.312,"starts_n":3},"last_start":{"deviation":3.0,"era_est":9.0,"ip":5.0},"trend_flags":["Outperforming xERA: ERA (3.07) << xERA (4.09)"]},"away_sp":{"name":"Wheeler, Zack","mlbam_id":554430,"throws":null,"season":{"xera":3.16,"xba":0.23,"whiff_pct":0.181,"chase_pct":0.405,"k_pct":0.247,"bb_pct":null,"rv100":null,"era":1.67,"ip":null},"recent":{"k_pct":0.247,"bb_pct":0.027,"whiff_pct":0.181,"chase_pct":0.405,"starts_n":3},"last_start":{"deviation":-3.0,"era_est":0.0,"ip":6.0},"trend_flags":["Outperforming xERA: ERA (1.67) << xERA (3.16)"]},"home_lineup":[],"away_lineup":[],"lineup_status":"tbd","prediction":{"home_win_pct":0.4349,"away_win_pct":0.5651,"predicted_home_runs":3.9,"predicted_away_runs":4.0,"predicted_total":7.9,"narrative":"Wheeler's elite peripherals (24.7% K-rate, 2.7% BB-rate) and exceptional recent form (1.67 ERA) anchor a notable model edge favoring the Phillies, despite Wrobleski's park-friendly home assignment and ERA outperformance. The pitcher score differential of -0.117 signals the model views this matchup as undervalued for Philadelphia, with Vegas pricing in nearly even odds while the Phillies command 56.5% implied win probability. Key caveat: both starters show significant ERA-xERA deviation in opposite directions (Wheeler's -3.00 last-start dip, Wrobleski's +3.00 spike), and lineups remain TBD\u2014any late scratches or platoon adjustments could materially shift the edge.","model_edge_ml":-0.0861,"pitcher_score_diff":-0.117,"pick_tier":null,"model_signals":{"pitcher_score_home":0.469,"pitcher_score_away":0.586,"lineup_score_home":0.5,"lineup_score_away":0.5,"comps_home_win_rate":0.4667,"comps_count":30,"park_modifier":-0.003,"weather_modifier":0.0,"rest_modifier":0.0,"home_rest_days":1,"away_rest_days":1,"bullpen_xera_home":null,"bullpen_xera_away":null,"bp_ip_last_3_home":null,"bp_ip_last_3_away":null,"last_start_dev_home":1.77,"last_start_dev_away":-2.78,"last_3_start_dev_home":1.77,"last_3_start_dev_away":-2.78,"last_start_pitches_home":null,"last_start_pitches_away":null,"umpire":null,"consensus_suppressed":false}},"away_record":{"wins":29,"losses":27,"streak":"W3","l10_w":6,"l10_l":4},"home_record":{"wins":36,"losses":20,"streak":"W5","l10_w":8,"l10_l":2}}]}